Workbook
Name aporte: Planilha1!$D$18
Name qtd_anos: Planilha1!$D$19
Name rendimento_carteira: Planilha1!$D$14
Name salario: Planilha1!$D$13
Name sugestao_investimento: Planilha1!$D$15
Name taxa_mensal: Planilha1!$D$20

Sheet Planilha1
B12: Configurações
B13: Salário | D13: 5000
B14: Rendimento Carteira | D14: 0.01
B15: Sugestão de Investimento | D15: =D13*30% -> 1500
B17: INVESTIMENTO MENSAL
B18: Quanto investir por mês? | D18: 500
B19: Por quantos anos? | D19: 5
B20: Taxa de rendimento mensal? | D20: 0.01079
B21: Patrimônio acumulado | D21: =FV(taxa_mensal,qtd_anos*12,(-1)*aporte) -> 41888.457
B22: Dividendos mensais | D22: =D21*rendimento_carteira -> 418.88457
B24: Cenários | D24: Rendimentos
A25: 2 | B25: Quanto em 2 anos? | C25: =FV($D$20,A25*12,$D$18*(-1)) -> 13613.814 | D25: =C25*rendimento_carteira -> 136.13814
A26: 5 | B26: Quanto em 5 anos? | C26: =FV($D$20,A26*12,$D$18*(-1)) -> 41888.457 | D26: =C26*rendimento_carteira -> 418.88457
A27: 10 | B27: Quanto em 10 anos? | C27: =FV($D$20,A27*12,$D$18*(-1)) -> 121642.11 | D27: =C27*rendimento_carteira -> 1216.4211
A28: 20 | B28: Quanto em 20 anos? | C28: =FV($D$20,A28*12,$D$18*(-1)) -> 562599.2 | D28: =C28*rendimento_carteira -> 5625.992
A29: 30 | B29: Quanto em 30 anos? | C29: =FV($D$20,A29*12,$D$18*(-1)) -> 2161084.8 | D29: =C29*rendimento_carteira -> 21610.848
B33: Perfil | D33: Agressivo
B34: Valor a ser investido por mês | D34: =aporte -> 500
B36: TIPO DE FIII | C36: Percentual Sugerido | D36: Valores
B37: PAPEL | C37: =VLOOKUP($D$33&"-"&B37,Planilha2!B3:E21,4,FALSE) -> 0.5 | D37: =C37*$D$34 -> 250
B38: TIJOLO | C38: =VLOOKUP($D$33&"-"&B38,Planilha2!B4:E22,4,FALSE) -> 0.1 | D38: =C38*$D$34 -> 50
B39: HÍBRIDOS | C39: =VLOOKUP($D$33&"-"&B39,Planilha2!B5:E23,4,FALSE) -> 0.05 | D39: =C39*$D$34 -> 25
B40: FOFs | C40: =VLOOKUP($D$33&"-"&B40,Planilha2!B6:E24,4,FALSE) -> 0.05 | D40: =C40*$D$34 -> 25
B41: DESENVOLVIMENTO | C41: =VLOOKUP($D$33&"-"&B41,Planilha2!B7:E25,4,FALSE) -> 0.2 | D41: =C41*$D$34 -> 100
B42: HOTELARIAS | C42: =VLOOKUP($D$33&"-"&B42,Planilha2!B8:E26,4,FALSE) -> 0.1 | D42: =C42*$D$34 -> 50
D43: =SUM(D37:D42) -> 500

Sheet Planilha2
B3: Chave | C3: Perfil | D3: TIPO DE FIII | E3: Percentual Sugerido
B4: =C4&"-"&D4 -> Conservador-PAPEL | C4: Conservador | D4: PAPEL | E4: 0.3
B5: =C5&"-"&D5 -> Conservador-TIJOLO | C5: Conservador | D5: TIJOLO | E5: 0.5 | G5: =B11 -> Moderado-TIJOLO | H5: =VLOOKUP(G5,$B$3:$E$21,4,FALSE) -> 0.35
B6: =C6&"-"&D6 -> Conservador-HÍBRIDOS | C6: Conservador | D6: HÍBRIDOS | E6: 0.1
B7: =C7&"-"&D7 -> Conservador-FOFs | C7: Conservador | D7: FOFs | E7: 0.1
B8: =C8&"-"&D8 -> Conservador-DESENVOLVIMENTO | C8: Conservador | D8: DESENVOLVIMENTO | E8: 0
B9: =C9&"-"&D9 -> Conservador-HOTELARIAS | C9: Conservador | D9: HOTELARIAS | E9: 0
B10: =C10&"-"&D10 -> Moderado-PAPEL | C10: Moderado | D10: PAPEL | E10: 0.32
B11: =C11&"-"&D11 -> Moderado-TIJOLO | C11: Moderado | D11: TIJOLO | E11: 0.35
B12: =C12&"-"&D12 -> Moderado-HÍBRIDOS | C12: Moderado | D12: HÍBRIDOS | E12: 0.08
B13: =C13&"-"&D13 -> Moderado-FOFs | C13: Moderado | D13: FOFs | E13: 0.1
B14: =C14&"-"&D14 -> Moderado-DESENVOLVIMENTO | C14: Moderado | D14: DESENVOLVIMENTO | E14: 0.1
B15: =C15&"-"&D15 -> Moderado-HOTELARIAS | C15: Moderado | D15: HOTELARIAS | E15: 0.1
B16: =C16&"-"&D16 -> Agressivo-PAPEL | C16: Agressivo | D16: PAPEL | E16: 0.5
B17: =C17&"-"&D17 -> Agressivo-TIJOLO | C17: Agressivo | D17: TIJOLO | E17: 0.1
... B21: =C21&"-"&D21 -> Agressivo-HOTELARIAS | C21: Agressivo | D21: HOTELARIAS | E21: 0.1
